{
 "AssignmentId": "386CSBG1O0BVQ0Q6L086OC7UFDZ6Q5",
 "WorkerId": "26995864e68ab82f604ded04fb94cf63",
 "HITId": "336OE47KI29I333Z8FAI49AO3MPVWW",
 "AssignmentStatus": "Approved",
 "AutoApprovalTime": "2020-02-18T23:04:22.000Z",
 "AcceptTime": "2020-02-18T22:51:39.000Z",
 "SubmitTime": "2020-02-18T22:59:22.000Z",
 "ApprovalTime": "2020-02-18T23:05:13.000Z",
 "answers": {
  "data": {
   "responses": "\"rt\",\"responses\",\"locator\",\"trial_type\",\"trial_index\",\"time_elapsed\",\"internal_node_id\"\r\n\"22032.01500000432\",\"{\"\"Q0\"\":\"\"bird\"\"}\",\"lookup-code-0\",\"survey-text\",\"3\",\"59513\",\"0.0-3.0-0.0-0.0\"\r\n\"9581.175000057556\",\"{\"\"Q0\"\":\"\"art\"\"}\",\"\",\"survey-text\",\"5\",\"72562\",\"0.0-5.0-0.0-0.0\"\r\n\"4022.960000031162\",\"{\"\"Q0\"\":\"\"sidd\"\"}\",\"\",\"survey-text\",\"7\",\"78603\",\"0.0-7.0\"\r\n\"6373.0649999924935\",\"{\"\"Q0\"\":\"\"bird\"\"}\",\"\",\"survey-text\",\"10\",\"92981\",\"0.0-10.0\"\r\n\"5482.739999948535\",\"{\"\"Q0\"\":\"\"plane\"\"}\",\"\",\"survey-text\",\"12\",\"99317\",\"0.0-12.0\"\r\n\"43248.51999996463\",\"{\"\"Q0\"\":\"\"weird shape with 5 legs\"\"}\",\"\",\"survey-text\",\"15\",\"146474\",\"0.0-15.0-0.0\"\r\n\"6092.854999995325\",\"{\"\"Q0\"\":\"\"pen\"\"}\",\"\",\"survey-text\",\"17\",\"155171\",\"0.0-15.0-0.1\"\r\n\"5090.105000010226\",\"{\"\"Q0\"\":\"\"pen\"\"}\",\"\",\"survey-text\",\"19\",\"161364\",\"0.0-15.0-0.2\"\r\n\"3362.444999977015\",\"{\"\"Q0\"\":\"\"pen\"\"}\",\"\",\"survey-text\",\"21\",\"166581\",\"0.0-15.0-0.3\"\r\n\"11772.50500000082\",\"{\"\"Q0\"\":\"\"something that holds a rope\"\"}\",\"\",\"survey-text\",\"23\",\"179206\",\"0.0-15.0-0.4\"\r\n\"5243.475000024773\",\"{\"\"Q0\"\":\"\"flower\"\"}\",\"\",\"survey-text\",\"25\",\"186304\",\"0.0-15.0-0.5\"\r\n\"31825.929999991786\",\"{\"\"Q0\"\":\"\"weird shape with many extrusions, like 2 balls\"\"}\",\"\",\"survey-text\",\"27\",\"219484\",\"0.0-15.0-0.6\"\r\n\"21217.495000048075\",\"{\"\"Q0\"\":\"\"weird spherical shape with many extrusions\"\"}\",\"\",\"survey-text\",\"29\",\"242054\",\"0.0-15.0-0.7\"\r\n\"10538.530000019819\",\"{\"\"Q0\"\":\"\"scorpion\"\"}\",\"\",\"survey-text\",\"31\",\"253696\",\"0.0-15.0-0.8\"\r\n\"13058.0600000103\",\"{\"\"Q0\"\":\"\"puzzle blocks\"\"}\",\"\",\"survey-text\",\"33\",\"268858\",\"0.0-15.0-0.9\"\r\n\"6845.4299999866635\",\"{\"\"Q0\"\":\"\"puzzle blocks\"\"}\",\"\",\"survey-text\",\"35\",\"278307\",\"0.0-15.0-0.10\"\r\n\"5019.889999995939\",\"{\"\"Q0\"\":\"\"puzzle blocks\"\"}\",\"\",\"survey-text\",\"37\",\"284179\",\"0.0-15.0-0.11\"\r\n\"3165.385000000242\",\"{\"\"Q0\"\":\"\"tree\"\"}\",\"\",\"survey-text\",\"39\",\"289948\",\"0.0-15.0-0.12\"\r\n\"18237.005000002682\",\"{\"\"Q0\"\":\"\"donut shape with 4 legs\"\"}\",\"\",\"survey-text\",\"41\",\"310038\",\"0.0-15.0-0.13\"\r\n\"4428.5950000048615\",\"{\"\"Q0\"\":\"\"cup\"\"}\",\"\",\"survey-text\",\"43\",\"317071\",\"0.0-15.0-0.14\"\r\n\"4461.780000012368\",\"{\"\"Q0\"\":\"\"dice\"\"}\",\"\",\"survey-text\",\"45\",\"323136\",\"0.0-15.0-0.15\"\r\n",
   "trial_info": [
    [
     "<img src = 'img/practiceTarget1.jpg' class='target'>",
     "<img src='img/practiceDistractor1.jpg' class='image'>"
    ],
    [
     "<img src='img/practiceDistractor2.jpg' class='image'>",
     "<img src ='img/practiceTarget2.jpg' class='target'>"
    ],
    [
     [
      "<img src='img/E.jpg' class='image'>",
      "<img src='img/5.jpg' class='target'>"
     ],
     [
      "<img src='img/D.jpg' class='target'>",
      "<img src='img/16.jpg' class='image'>"
     ],
     [
      "<img src='img/D.jpg' class='target'>",
      "<img src='img/10.jpg' class='image'>"
     ],
     [
      "<img src='img/3.jpg' class='image'>",
      "<img src='img/D.jpg' class='target'>"
     ],
     [
      "<img src='img/6.jpg' class='target'>",
      "<img src='img/C.jpg' class='image'>"
     ],
     [
      "<img src='img/12.jpg' class='image'>",
      "<img src='img/L.jpg' class='target'>"
     ],
     [
      "<img src='img/1.jpg' class='target'>",
      "<img src='img/B.jpg' class='image'>"
     ],
     [
      "<img src='img/11.jpg' class='target'>",
      "<img src='img/D.jpg' class='image'>"
     ]
    ],
    [
     [
      "<img src='img/N.jpg' class='target'>",
      "<img src='img/7.jpg' class='image'>"
     ],
     [
      "<img src='img/15.jpg' class='target'>",
      "<img src='img/K.jpg' class='image'>"
     ],
     [
      "<img src='img/15.jpg' class='target'>",
      "<img src='img/A.jpg' class='image'>"
     ],
     [
      "<img src='img/G.jpg' class='image'>",
      "<img src='img/15.jpg' class='target'>"
     ],
     [
      "<img src='img/J.jpg' class='target'>",
      "<img src='img/8.jpg' class='image'>"
     ],
     [
      "<img src='img/F.jpg' class='image'>",
      "<img src='img/4.jpg' class='target'>"
     ],
     [
      "<img src='img/2.jpg' class='image'>",
      "<img src='img/M.jpg' class='target'>"
     ],
     [
      "<img src='img/15.jpg' class='image'>",
      "<img src='img/H.jpg' class='target'>"
     ]
    ]
   ]
  }
 }
}