{
 "AssignmentId": "3JJVG1YBECMC3QO3XZ1B1HYV5VQB5J",
 "WorkerId": "b09b6252493a4363221e5ca2180bffb8",
 "HITId": "34R3P23QHSQDL28F3QTEP8JFXFPWH0",
 "AssignmentStatus": "Approved",
 "AutoApprovalTime": "2020-04-22T18:35:44.000Z",
 "AcceptTime": "2020-04-22T18:22:12.000Z",
 "SubmitTime": "2020-04-22T18:30:44.000Z",
 "ApprovalTime": "2020-04-22T18:36:20.000Z",
 "answers": {
  "data": {
   "responses": "\"rt\",\"responses\",\"locator\",\"trial_type\",\"trial_index\",\"time_elapsed\",\"internal_node_id\"\r\n\"11830.000000016298\",\"{\"\"Q0\"\":\"\"bird\"\"}\",\"lookup-code-0\",\"survey-text\",\"3\",\"165852\",\"0.0-3.0-0.0-0.0\"\r\n\"16163.780000002589\",\"{\"\"Q0\"\":\"\"art\"\"}\",\"\",\"survey-text\",\"5\",\"200117\",\"0.0-5.0-0.0-0.0\"\r\n\"8334.399999992456\",\"{\"\"Q0\"\":\"\"jo\"\"}\",\"\",\"survey-text\",\"7\",\"212988\",\"0.0-7.0\"\r\n\"14970.975000003818\",\"{\"\"Q0\"\":\"\"bird\"\"}\",\"\",\"survey-text\",\"10\",\"235964\",\"0.0-10.0\"\r\n\"6641.064999974333\",\"{\"\"Q0\"\":\"\"plane\"\"}\",\"\",\"survey-text\",\"12\",\"243460\",\"0.0-12.0\"\r\n\"16267.824999988079\",\"{\"\"Q0\"\":\"\"weird legs object\"\"}\",\"\",\"survey-text\",\"16\",\"266044\",\"0.0-16.0\"\r\n\"8129.030000010971\",\"{\"\"Q0\"\":\"\"plunger bottom\"\"}\",\"\",\"survey-text\",\"19\",\"278780\",\"0.0-19.0\"\r\n\"11108.34999999497\",\"{\"\"Q0\"\":\"\"seatbelt lock\"\"}\",\"\",\"survey-text\",\"22\",\"294244\",\"0.0-22.0\"\r\n\"18473.549999995157\",\"{\"\"Q0\"\":\"\"cymbals\"\"}\",\"\",\"survey-text\",\"25\",\"318324\",\"0.0-25.0\"\r\n\"17170.524999994086\",\"{\"\"Q0\"\":\"\"finger bandaid\"\"}\",\"\",\"survey-text\",\"28\",\"340099\",\"0.0-28.0\"\r\n\"6022.760000021663\",\"{\"\"Q0\"\":\"\"finger bandaid\"\"}\",\"\",\"survey-text\",\"31\",\"350979\",\"0.0-31.0\"\r\n\"9902.53500000108\",\"{\"\"Q0\"\":\"\"finger splint\"\"}\",\"\",\"survey-text\",\"34\",\"364987\",\"0.0-34.0\"\r\n\"4285.0000000034925\",\"{\"\"Q0\"\":\"\"plunger\"\"}\",\"\",\"survey-text\",\"37\",\"375379\",\"0.0-37.0\"\r\n\"10222.194999980275\",\"{\"\"Q0\"\":\"\"paper art\"\"}\",\"\",\"survey-text\",\"40\",\"389708\",\"0.0-40.0\"\r\n\"4335.5049999954645\",\"{\"\"Q0\"\":\"\"crab\"\"}\",\"\",\"survey-text\",\"43\",\"397900\",\"0.0-43.0\"\r\n\"18811.92999999621\",\"{\"\"Q0\"\":\"\"plastic circle pieces\"\"}\",\"\",\"survey-text\",\"46\",\"421068\",\"0.0-46.0\"\r\n\"4684.565000003204\",\"{\"\"Q0\"\":\"\"ring\"\"}\",\"\",\"survey-text\",\"49\",\"430107\",\"0.0-49.0\"\r\n\"21024.930000014137\",\"{\"\"Q0\"\":\"\"round plane\"\"}\",\"\",\"survey-text\",\"52\",\"455988\",\"0.0-52.0\"\r\n\"5904.450000001816\",\"{\"\"Q0\"\":\"\"round plane\"\"}\",\"\",\"survey-text\",\"55\",\"465748\",\"0.0-55.0\"\r\n\"6385.145000007469\",\"{\"\"Q0\"\":\"\"round plane\"\"}\",\"\",\"survey-text\",\"58\",\"477739\",\"0.0-58.0\"\r\n\"2262.170000001788\",\"{\"\"Q0\"\":\"\"car\"\"}\",\"\",\"survey-text\",\"61\",\"483859\",\"0.0-61.0\"\r\n",
   "trial_info": [
    [
     "<img src = 'img/practiceTarget1.jpg' class='target'>",
     "<img src='img/practiceDistractor1.jpg' class='image'>"
    ],
    [
     "<img src='img/practiceDistractor2.jpg' class='image'>",
     "<img src ='img/practiceTarget2.jpg' class='target'>"
    ],
    [
     [
      "<img src='img/15.jpg' class='image'>",
      "<img src='img/27.jpg' class='target'>"
     ],
     [
      "<img src='img/9.jpg' class='image'>",
      "<img src='img/20.jpg' class='target'>"
     ],
     [
      "<img src='img/4.jpg' class='image'>",
      "<img src='img/6.jpg' class='target'>"
     ],
     [
      "<img src='img/12.jpg' class='target'>",
      "<img src='img/3.jpg' class='image'>"
     ],
     [
      "<img src='img/7.jpg' class='target'>",
      "<img src='img/25.jpg' class='image'>"
     ],
     [
      "<img src='img/26.jpg' class='image'>",
      "<img src='img/7.jpg' class='target'>"
     ],
     [
      "<img src='img/19.jpg' class='image'>",
      "<img src='img/7.jpg' class='target'>"
     ],
     [
      "<img src='img/7.jpg' class='image'>",
      "<img src='img/10.jpg' class='target'>"
     ],
     [
      "<img src='img/H.jpg' class='image'>",
      "<img src='img/17.jpg' class='target'>"
     ],
     [
      "<img src='img/N.jpg' class='target'>",
      "<img src='img/5.jpg' class='image'>"
     ],
     [
      "<img src='img/K.jpg' class='image'>",
      "<img src='img/23.jpg' class='target'>"
     ],
     [
      "<img src='img/2.jpg' class='image'>",
      "<img src='img/F.jpg' class='target'>"
     ],
     [
      "<img src='img/M.jpg' class='image'>",
      "<img src='img/16.jpg' class='target'>"
     ],
     [
      "<img src='img/C.jpg' class='image'>",
      "<img src='img/16.jpg' class='target'>"
     ],
     [
      "<img src='img/16.jpg' class='target'>",
      "<img src='img/B.jpg' class='image'>"
     ],
     [
      "<img src='img/I.jpg' class='target'>",
      "<img src='img/16.jpg' class='image'>"
     ]
    ]
   ]
  }
 }
}