{
 "AssignmentId": "3XXU1SWE8NK8P9XAUFV3PBIY65UA02",
 "WorkerId": "0797fae9c0d8e546338f1ecb44eb8e5e",
 "HITId": "3NCN4N1H1G6D7VWFBXSV7E3Q9QHBN9",
 "AssignmentStatus": "Approved",
 "AutoApprovalTime": "2020-04-22T18:34:04.000Z",
 "AcceptTime": "2020-04-22T18:22:28.000Z",
 "SubmitTime": "2020-04-22T18:29:04.000Z",
 "ApprovalTime": "2020-04-22T18:34:20.000Z",
 "answers": {
  "data": {
   "responses": "\"rt\",\"responses\",\"locator\",\"trial_type\",\"trial_index\",\"time_elapsed\",\"internal_node_id\"\r\n\"9902.434999999969\",\"{\"\"Q0\"\":\"\"bird\"\"}\",\"lookup-code-0\",\"survey-text\",\"3\",\"53436\",\"0.0-3.0-0.0-0.0\"\r\n\"11298.109999999724\",\"{\"\"Q0\"\":\"\"art\"\"}\",\"\",\"survey-text\",\"5\",\"66486\",\"0.0-5.0-0.0-0.0\"\r\n\"13072.019999999611\",\"{\"\"Q0\"\":\"\"Rose\"\"}\",\"\",\"survey-text\",\"7\",\"82656\",\"0.0-7.0\"\r\n\"3645.6250000010186\",\"{\"\"Q0\"\":\"\"bird\"\"}\",\"\",\"survey-text\",\"10\",\"94340\",\"0.0-10.0\"\r\n\"3379.144999998971\",\"{\"\"Q0\"\":\"\"plane\"\"}\",\"\",\"survey-text\",\"12\",\"99840\",\"0.0-12.0\"\r\n\"10801.039999998466\",\"{\"\"Q0\"\":\"\"bell shaped item\"\"}\",\"\",\"survey-text\",\"16\",\"117282\",\"0.0-16.0\"\r\n\"17375.325000000885\",\"{\"\"Q0\"\":\"\"folded upright cloth\"\"}\",\"\",\"survey-text\",\"19\",\"140793\",\"0.0-19.0\"\r\n\"10615.294999999605\",\"{\"\"Q0\"\":\"\"spinning top \"\"}\",\"\",\"survey-text\",\"22\",\"156558\",\"0.0-22.0\"\r\n\"11541.779999999562\",\"{\"\"Q0\"\":\"\"dog bone \"\"}\",\"\",\"survey-text\",\"25\",\"172492\",\"0.0-25.0\"\r\n\"13345.290000001114\",\"{\"\"Q0\"\":\"\"round with a hole upper left\"\"}\",\"\",\"survey-text\",\"28\",\"190974\",\"0.0-28.0\"\r\n\"15688.00999999803\",\"{\"\"Q0\"\":\"\"round with a hole upper left\"\"}\",\"\",\"survey-text\",\"31\",\"211040\",\"0.0-31.0\"\r\n\"14444.155000001047\",\"{\"\"Q0\"\":\"\"round with hole upper left\"\"}\",\"\",\"survey-text\",\"34\",\"229620\",\"0.0-34.0\"\r\n\"11326.430000000983\",\"{\"\"Q0\"\":\"\"fuzzy with antennas\"\"}\",\"\",\"survey-text\",\"37\",\"245094\",\"0.0-37.0\"\r\n\"7473.105000000942\",\"{\"\"Q0\"\":\"\"round wood with slots\"\"}\",\"\",\"survey-text\",\"40\",\"257261\",\"0.0-40.0\"\r\n\"2858.6599999980535\",\"{\"\"Q0\"\":\"\"fork\"\"}\",\"\",\"survey-text\",\"43\",\"265010\",\"0.0-43.0\"\r\n\"18169.77500000212\",\"{\"\"Q0\"\":\"\"A claw \"\"}\",\"\",\"survey-text\",\"46\",\"289307\",\"0.0-46.0\"\r\n\"2770.4049999992712\",\"{\"\"Q0\"\":\"\"chair\"\"}\",\"\",\"survey-text\",\"49\",\"298217\",\"0.0-49.0\"\r\n\"16432.62499999767\",\"{\"\"Q0\"\":\"\"not the cup\"\"}\",\"\",\"survey-text\",\"52\",\"319306\",\"0.0-52.0\"\r\n\"9612.744999998598\",\"{\"\"Q0\"\":\"\"like a dice \"\"}\",\"\",\"survey-text\",\"55\",\"333290\",\"0.0-55.0\"\r\n\"18536.299999999697\",\"{\"\"Q0\"\":\"\"square with pieces coming off it\"\"}\",\"\",\"survey-text\",\"58\",\"356472\",\"0.0-58.0\"\r\n\"3203.914999998233\",\"{\"\"Q0\"\":\"\"pen\"\"}\",\"\",\"survey-text\",\"61\",\"363799\",\"0.0-61.0\"\r\n",
   "trial_info": [
    [
     "<img src = 'img/practiceTarget1.jpg' class='target'>",
     "<img src='img/practiceDistractor1.jpg' class='image'>"
    ],
    [
     "<img src='img/practiceDistractor2.jpg' class='image'>",
     "<img src ='img/practiceTarget2.jpg' class='target'>"
    ],
    [
     [
      "<img src='img/25.jpg' class='image'>",
      "<img src='img/20.jpg' class='target'>"
     ],
     [
      "<img src='img/7.jpg' class='target'>",
      "<img src='img/1.jpg' class='image'>"
     ],
     [
      "<img src='img/19.jpg' class='image'>",
      "<img src='img/12.jpg' class='target'>"
     ],
     [
      "<img src='img/5.jpg' class='target'>",
      "<img src='img/8.jpg' class='image'>"
     ],
     [
      "<img src='img/26.jpg' class='target'>",
      "<img src='img/17.jpg' class='image'>"
     ],
     [
      "<img src='img/21.jpg' class='image'>",
      "<img src='img/26.jpg' class='target'>"
     ],
     [
      "<img src='img/26.jpg' class='target'>",
      "<img src='img/3.jpg' class='image'>"
     ],
     [
      "<img src='img/26.jpg' class='image'>",
      "<img src='img/4.jpg' class='target'>"
     ],
     [
      "<img src='img/23.jpg' class='target'>",
      "<img src='img/C.jpg' class='image'>"
     ],
     [
      "<img src='img/16.jpg' class='image'>",
      "<img src='img/G.jpg' class='target'>"
     ],
     [
      "<img src='img/27.jpg' class='target'>",
      "<img src='img/B.jpg' class='image'>"
     ],
     [
      "<img src='img/E.jpg' class='target'>",
      "<img src='img/6.jpg' class='image'>"
     ],
     [
      "<img src='img/M.jpg' class='image'>",
      "<img src='img/11.jpg' class='target'>"
     ],
     [
      "<img src='img/11.jpg' class='target'>",
      "<img src='img/I.jpg' class='image'>"
     ],
     [
      "<img src='img/F.jpg' class='image'>",
      "<img src='img/11.jpg' class='target'>"
     ],
     [
      "<img src='img/D.jpg' class='target'>",
      "<img src='img/11.jpg' class='image'>"
     ]
    ]
   ]
  }
 }
}