{
 "AssignmentId": "39GXDJN2OU3AZM5B0EZEED2SKK78VA",
 "WorkerId": "d1a31f361d368376b5f0cbb1270bd92b",
 "HITId": "324N5FAHSX0R839IJ1RFGYGTDCCVKN",
 "AssignmentStatus": "Approved",
 "AutoApprovalTime": "2019-09-13T20:49:19.000Z",
 "AcceptTime": "2019-09-13T19:51:45.000Z",
 "SubmitTime": "2019-09-13T20:44:19.000Z",
 "ApprovalTime": "2019-09-13T20:50:13.000Z",
 "answers": {
  "data": {
   "responses": "\"rt\",\"responses\",\"trial_type\",\"trial_index\",\"time_elapsed\",\"internal_node_id\"\r\n\"21242.925000377\",\"{\"\"Q0\"\":\"\"bird\"\"}\",\"survey-text\",\"3\",\"114457\",\"0.0-3.0\"\r\n\"10412.43499983102\",\"{\"\"Q0\"\":\"\"art\"\"}\",\"survey-text\",\"5\",\"128749\",\"0.0-5.0\"\r\n\"29490.334999747574\",\"{\"\"Q0\"\":\"\"Hans-Michel\"\"}\",\"survey-text\",\"7\",\"160405\",\"0.0-7.0\"\r\n\"9142.560000531375\",\"{\"\"Q0\"\":\"\"bird\"\"}\",\"survey-text\",\"10\",\"177553\",\"0.0-10.0\"\r\n\"8131.369999609888\",\"{\"\"Q0\"\":\"\"plane\"\"}\",\"survey-text\",\"12\",\"188789\",\"0.0-12.0\"\r\n\"8165.980000048876\",\"{\"\"Q0\"\":\"\"shoe\"\"}\",\"survey-text\",\"15\",\"200173\",\"0.0-15.0-0.0\"\r\n\"6023.474999703467\",\"{\"\"Q0\"\":\"\"fork\"\"}\",\"survey-text\",\"17\",\"208801\",\"0.0-15.0-0.1\"\r\n\"8274.000000208616\",\"{\"\"Q0\"\":\"\"apple\"\"}\",\"survey-text\",\"19\",\"219681\",\"0.0-15.0-0.2\"\r\n\"8955.269999802113\",\"{\"\"Q0\"\":\"\"chair\"\"}\",\"survey-text\",\"21\",\"230740\",\"0.0-15.0-0.3\"\r\n\"6261.919999495149\",\"{\"\"Q0\"\":\"\"pen\"\"}\",\"survey-text\",\"23\",\"238856\",\"0.0-15.0-0.4\"\r\n\"6251.7450004816055\",\"{\"\"Q0\"\":\"\"pen\"\"}\",\"survey-text\",\"25\",\"248212\",\"0.0-15.0-0.5\"\r\n\"6238.840000703931\",\"{\"\"Q0\"\":\"\"pen\"\"}\",\"survey-text\",\"27\",\"257556\",\"0.0-15.0-0.6\"\r\n\"6996.999999508262\",\"{\"\"Q0\"\":\"\"cat\"\"}\",\"survey-text\",\"29\",\"266408\",\"0.0-15.0-0.7\"\r\n\"9499.270000495017\",\"{\"\"Q0\"\":\"\"tall\"\"}\",\"survey-text\",\"31\",\"277012\",\"0.0-15.0-0.8\"\r\n\"15938.954999670386\",\"{\"\"Q0\"\":\"\"crunchy\"\"}\",\"survey-text\",\"33\",\"295556\",\"0.0-15.0-0.9\"\r\n\"10296.439999714494\",\"{\"\"Q0\"\":\"\"long\"\"}\",\"survey-text\",\"35\",\"307956\",\"0.0-15.0-0.10\"\r\n\"23221.084999851882\",\"{\"\"Q0\"\":\"\"ex\"\"}\",\"survey-text\",\"37\",\"333032\",\"0.0-15.0-0.11\"\r\n\"10942.43000075221\",\"{\"\"Q0\"\":\"\"tea\"\"}\",\"survey-text\",\"39\",\"347079\",\"0.0-15.0-0.12\"\r\n\"7823.289999738336\",\"{\"\"Q0\"\":\"\"tea\"\"}\",\"survey-text\",\"41\",\"356507\",\"0.0-15.0-0.13\"\r\n\"7776.420000009239\",\"{\"\"Q0\"\":\"\"tea\"\"}\",\"survey-text\",\"43\",\"366139\",\"0.0-15.0-0.14\"\r\n\"11082.070000469685\",\"{\"\"Q0\"\":\"\"y\"\"}\",\"survey-text\",\"45\",\"378575\",\"0.0-15.0-0.15\"\r\n",
   "trial_info": [
    [
     "<img src = 'img/practiceTarget1.jpg' class='target'>",
     "<img src='img/practiceDistractor1.jpg' class='image'>"
    ],
    [
     "<img src='img/practiceDistractor2.jpg' class='image'>",
     "<img src ='img/practiceTarget2.jpg' class='target'>"
    ],
    [
     [
      "<img src='img/C.jpg' class='target'>",
      "<img src='img/K.jpg' class='image'>"
     ],
     [
      "<img src='img/G.jpg' class='target'>",
      "<img src='img/F.jpg' class='image'>"
     ],
     [
      "<img src='img/A.jpg' class='target'>",
      "<img src='img/L.jpg' class='image'>"
     ],
     [
      "<img src='img/E.jpg' class='target'>",
      "<img src='img/I.jpg' class='image'>"
     ],
     [
      "<img src='img/I.jpg' class='image'>",
      "<img src='img/D.jpg' class='target'>"
     ],
     [
      "<img src='img/J.jpg' class='image'>",
      "<img src='img/D.jpg' class='target'>"
     ],
     [
      "<img src='img/H.jpg' class='image'>",
      "<img src='img/D.jpg' class='target'>"
     ],
     [
      "<img src='img/B.jpg' class='target'>",
      "<img src='img/D.jpg' class='image'>"
     ]
    ],
    [
     [
      "<img src='img/1.jpg' class='target'>",
      "<img src='img/7.jpg' class='image'>"
     ],
     [
      "<img src='img/6.jpg' class='image'>",
      "<img src='img/8.jpg' class='target'>"
     ],
     [
      "<img src='img/5.jpg' class='target'>",
      "<img src='img/12.jpg' class='image'>"
     ],
     [
      "<img src='img/11.jpg' class='target'>",
      "<img src='img/2.jpg' class='image'>"
     ],
     [
      "<img src='img/9.jpg' class='target'>",
      "<img src='img/2.jpg' class='image'>"
     ],
     [
      "<img src='img/9.jpg' class='target'>",
      "<img src='img/3.jpg' class='image'>"
     ],
     [
      "<img src='img/9.jpg' class='target'>",
      "<img src='img/10.jpg' class='image'>"
     ],
     [
      "<img src='img/4.jpg' class='target'>",
      "<img src='img/9.jpg' class='image'>"
     ]
    ]
   ]
  }
 }
}