{
 "AssignmentId": "32Z9ZLUT1M982DX72676WY1JRAZOH2",
 "WorkerId": "1db9aa7214da1023562d583e1b369f14",
 "HITId": "324N5FAHSX0R839IJ1RFGYGTDCCVKN",
 "AssignmentStatus": "Approved",
 "AutoApprovalTime": "2019-09-13T20:12:45.000Z",
 "AcceptTime": "2019-09-13T19:49:26.000Z",
 "SubmitTime": "2019-09-13T20:07:45.000Z",
 "ApprovalTime": "2019-09-13T20:13:13.000Z",
 "answers": {
  "data": {
   "responses": "\"rt\",\"responses\",\"trial_type\",\"trial_index\",\"time_elapsed\",\"internal_node_id\"\r\n\"7567.525000005844\",\"{\"\"Q0\"\":\"\"bird\"\"}\",\"survey-text\",\"3\",\"614893\",\"0.0-3.0\"\r\n\"10355.749999987893\",\"{\"\"Q0\"\":\"\"art\"\"}\",\"survey-text\",\"5\",\"631600\",\"0.0-5.0\"\r\n\"11793.790000010631\",\"{\"\"Q0\"\":\"\"npc tom\"\"}\",\"survey-text\",\"7\",\"645784\",\"0.0-7.0\"\r\n\"2863.6249999981374\",\"{\"\"Q0\"\":\"\"bird\"\"}\",\"survey-text\",\"10\",\"656672\",\"0.0-10.0\"\r\n\"4492.655000009108\",\"{\"\"Q0\"\":\"\"airplane\"\"}\",\"survey-text\",\"12\",\"662536\",\"0.0-12.0\"\r\n\"2593.930000002729\",\"{\"\"Q0\"\":\"\"ring\"\"}\",\"survey-text\",\"15\",\"667344\",\"0.0-15.0-0.0\"\r\n\"2399.0199999971082\",\"{\"\"Q0\"\":\"\"chair\"\"}\",\"survey-text\",\"17\",\"670619\",\"0.0-15.0-0.1\"\r\n\"1837.6699999935227\",\"{\"\"Q0\"\":\"\"dice\"\"}\",\"survey-text\",\"19\",\"673576\",\"0.0-15.0-0.2\"\r\n\"6971.765000009327\",\"{\"\"Q0\"\":\"\"butterfly\"\"}\",\"survey-text\",\"21\",\"681928\",\"0.0-15.0-0.3\"\r\n\"1628.1350000062957\",\"{\"\"Q0\"\":\"\"fork\"\"}\",\"survey-text\",\"23\",\"684432\",\"0.0-15.0-0.4\"\r\n\"2433.0800000025192\",\"{\"\"Q0\"\":\"\"fork\"\"}\",\"survey-text\",\"25\",\"687984\",\"0.0-15.0-0.5\"\r\n\"2832.4350000038976\",\"{\"\"Q0\"\":\"\"fork\"\"}\",\"survey-text\",\"27\",\"692185\",\"0.0-15.0-0.6\"\r\n\"1857.7400000067428\",\"{\"\"Q0\"\":\"\"cat\"\"}\",\"survey-text\",\"29\",\"697161\",\"0.0-15.0-0.7\"\r\n\"5785.814999995637\",\"{\"\"Q0\"\":\"\"tool\"\"}\",\"survey-text\",\"31\",\"704816\",\"0.0-15.0-0.8\"\r\n\"6689.904999991995\",\"{\"\"Q0\"\":\"\"long\"\"}\",\"survey-text\",\"33\",\"713376\",\"0.0-15.0-0.9\"\r\n\"3629.9899999867193\",\"{\"\"Q0\"\":\"\"star\"\"}\",\"survey-text\",\"35\",\"717882\",\"0.0-15.0-0.10\"\r\n\"2475.8849999925587\",\"{\"\"Q0\"\":\"\"long\"\"}\",\"survey-text\",\"37\",\"722979\",\"0.0-15.0-0.11\"\r\n\"9028.729999990901\",\"{\"\"Q0\"\":\"\"y shaped\"\"}\",\"survey-text\",\"39\",\"733377\",\"0.0-15.0-0.12\"\r\n\"2668.409999998403\",\"{\"\"Q0\"\":\"\"y shaped\"\"}\",\"survey-text\",\"41\",\"736913\",\"0.0-15.0-0.13\"\r\n\"6191.444999989471\",\"{\"\"Q0\"\":\"\"y shaped \"\"}\",\"survey-text\",\"43\",\"744233\",\"0.0-15.0-0.14\"\r\n\"2883.7599999969825\",\"{\"\"Q0\"\":\"\"crown\"\"}\",\"survey-text\",\"45\",\"749758\",\"0.0-15.0-0.15\"\r\n",
   "trial_info": [
    [
     "<img src = 'img/practiceTarget1.jpg' class='target'>",
     "<img src='img/practiceDistractor1.jpg' class='image'>"
    ],
    [
     "<img src='img/practiceDistractor2.jpg' class='image'>",
     "<img src ='img/practiceTarget2.jpg' class='target'>"
    ],
    [
     [
      "<img src='img/F.jpg' class='target'>",
      "<img src='img/L.jpg' class='image'>"
     ],
     [
      "<img src='img/D.jpg' class='image'>",
      "<img src='img/E.jpg' class='target'>"
     ],
     [
      "<img src='img/J.jpg' class='image'>",
      "<img src='img/H.jpg' class='target'>"
     ],
     [
      "<img src='img/A.jpg' class='image'>",
      "<img src='img/K.jpg' class='target'>"
     ],
     [
      "<img src='img/G.jpg' class='target'>",
      "<img src='img/A.jpg' class='image'>"
     ],
     [
      "<img src='img/C.jpg' class='image'>",
      "<img src='img/G.jpg' class='target'>"
     ],
     [
      "<img src='img/I.jpg' class='image'>",
      "<img src='img/G.jpg' class='target'>"
     ],
     [
      "<img src='img/B.jpg' class='target'>",
      "<img src='img/G.jpg' class='image'>"
     ]
    ],
    [
     [
      "<img src='img/12.jpg' class='target'>",
      "<img src='img/5.jpg' class='image'>"
     ],
     [
      "<img src='img/7.jpg' class='target'>",
      "<img src='img/6.jpg' class='image'>"
     ],
     [
      "<img src='img/11.jpg' class='target'>",
      "<img src='img/2.jpg' class='image'>"
     ],
     [
      "<img src='img/9.jpg' class='target'>",
      "<img src='img/8.jpg' class='image'>"
     ],
     [
      "<img src='img/4.jpg' class='target'>",
      "<img src='img/8.jpg' class='image'>"
     ],
     [
      "<img src='img/4.jpg' class='target'>",
      "<img src='img/10.jpg' class='image'>"
     ],
     [
      "<img src='img/4.jpg' class='target'>",
      "<img src='img/1.jpg' class='image'>"
     ],
     [
      "<img src='img/4.jpg' class='image'>",
      "<img src='img/3.jpg' class='target'>"
     ]
    ]
   ]
  }
 }
}