{
 "AssignmentId": "3D8YOU6S9F9NITXN29SBYD4JQBMU6D",
 "WorkerId": "ce53f1129b059a088ab6a07588aff229",
 "HITId": "3XT3KXP24ZNFNI4TIQYVRQLH9QC6I3",
 "AssignmentStatus": "Approved",
 "AutoApprovalTime": "2020-04-22T22:03:13.000Z",
 "AcceptTime": "2020-04-22T21:14:03.000Z",
 "SubmitTime": "2020-04-22T21:58:13.000Z",
 "ApprovalTime": "2020-04-22T22:03:20.000Z",
 "answers": {
  "data": {
   "responses": "\"rt\",\"responses\",\"locator\",\"trial_type\",\"trial_index\",\"time_elapsed\",\"internal_node_id\"\r\n\"3840.454999997746\",\"{\"\"Q0\"\":\"\"bird\"\"}\",\"lookup-code-0\",\"survey-text\",\"3\",\"73237\",\"0.0-3.0-0.0-0.0\"\r\n\"5829.385000019101\",\"{\"\"Q0\"\":\"\"art\"\"}\",\"\",\"survey-text\",\"5\",\"81276\",\"0.0-5.0-0.0-0.0\"\r\n\"4786.270000011427\",\"{\"\"Q0\"\":\"\"Dodo\"\"}\",\"\",\"survey-text\",\"7\",\"87203\",\"0.0-7.0\"\r\n\"9038.115000003017\",\"{\"\"Q0\"\":\"\"bird\"\"}\",\"\",\"survey-text\",\"10\",\"105583\",\"0.0-10.0\"\r\n\"3759.0000000200234\",\"{\"\"Q0\"\":\"\"plane\"\"}\",\"\",\"survey-text\",\"12\",\"112450\",\"0.0-12.0\"\r\n\"2511.73500000732\",\"{\"\"Q0\"\":\"\"apple\"\"}\",\"\",\"survey-text\",\"16\",\"120771\",\"0.0-16.0\"\r\n\"3398.139999975683\",\"{\"\"Q0\"\":\"\"rocket\"\"}\",\"\",\"survey-text\",\"19\",\"128278\",\"0.0-19.0\"\r\n\"7849.549999984447\",\"{\"\"Q0\"\":\"\"slip-on art\"\"}\",\"\",\"survey-text\",\"22\",\"140486\",\"0.0-22.0\"\r\n\"2822.2400000086054\",\"{\"\"Q0\"\":\"\"chair\"\"}\",\"\",\"survey-text\",\"25\",\"147166\",\"0.0-25.0\"\r\n\"2429.245000006631\",\"{\"\"Q0\"\":\"\"car\"\"}\",\"\",\"survey-text\",\"28\",\"154714\",\"0.0-28.0\"\r\n\"3221.6649999900255\",\"{\"\"Q0\"\":\"\"car\"\"}\",\"\",\"survey-text\",\"31\",\"162294\",\"0.0-31.0\"\r\n\"1572.6050000230316\",\"{\"\"Q0\"\":\"\"car\"\"}\",\"\",\"survey-text\",\"34\",\"169473\",\"0.0-34.0\"\r\n\"8969.704999995884\",\"{\"\"Q0\"\":\"\"cymbal looking item\"\"}\",\"\",\"survey-text\",\"37\",\"182299\",\"0.0-37.0\"\r\n\"9601.50000001886\",\"{\"\"Q0\"\":\"\"rubber sandal top\"\"}\",\"\",\"survey-text\",\"40\",\"196508\",\"0.0-40.0\"\r\n\"9203.00499998848\",\"{\"\"Q0\"\":\"\"wheeled object\"\"}\",\"\",\"survey-text\",\"43\",\"210067\",\"0.0-43.0\"\r\n\"15842.814999981783\",\"{\"\"Q0\"\":\"\"white art\"\"}\",\"\",\"survey-text\",\"46\",\"231517\",\"0.0-46.0\"\r\n\"16829.094999993686\",\"{\"\"Q0\"\":\"\"germ art\"\"}\",\"\",\"survey-text\",\"49\",\"254471\",\"0.0-49.0\"\r\n\"2754.1999999957625\",\"{\"\"Q0\"\":\"\"lego\"\"}\",\"\",\"survey-text\",\"52\",\"262833\",\"0.0-52.0\"\r\n\"6752.290000003995\",\"{\"\"Q0\"\":\"\"lego\"\"}\",\"\",\"survey-text\",\"55\",\"273695\",\"0.0-55.0\"\r\n\"2066.049999993993\",\"{\"\"Q0\"\":\"\"lego\"\"}\",\"\",\"survey-text\",\"58\",\"279617\",\"0.0-58.0\"\r\n\"4536.90999999526\",\"{\"\"Q0\"\":\"\"iceberg\"\"}\",\"\",\"survey-text\",\"61\",\"288763\",\"0.0-61.0\"\r\n",
   "trial_info": [
    [
     "<img src = 'img/practiceTarget1.jpg' class='target'>",
     "<img src='img/practiceDistractor1.jpg' class='image'>"
    ],
    [
     "<img src='img/practiceDistractor2.jpg' class='image'>",
     "<img src ='img/practiceTarget2.jpg' class='target'>"
    ],
    [
     [
      "<img src='img/5.jpg' class='image'>",
      "<img src='img/A.jpg' class='target'>"
     ],
     [
      "<img src='img/G.jpg' class='image'>",
      "<img src='img/16.jpg' class='target'>"
     ],
     [
      "<img src='img/7.jpg' class='target'>",
      "<img src='img/D.jpg' class='image'>"
     ],
     [
      "<img src='img/17.jpg' class='image'>",
      "<img src='img/E.jpg' class='target'>"
     ],
     [
      "<img src='img/20.jpg' class='image'>",
      "<img src='img/I.jpg' class='target'>"
     ],
     [
      "<img src='img/8.jpg' class='image'>",
      "<img src='img/I.jpg' class='target'>"
     ],
     [
      "<img src='img/22.jpg' class='image'>",
      "<img src='img/I.jpg' class='target'>"
     ],
     [
      "<img src='img/I.jpg' class='image'>",
      "<img src='img/12.jpg' class='target'>"
     ],
     [
      "<img src='img/26.jpg' class='image'>",
      "<img src='img/18.jpg' class='target'>"
     ],
     [
      "<img src='img/23.jpg' class='target'>",
      "<img src='img/25.jpg' class='image'>"
     ],
     [
      "<img src='img/4.jpg' class='target'>",
      "<img src='img/24.jpg' class='image'>"
     ],
     [
      "<img src='img/9.jpg' class='image'>",
      "<img src='img/19.jpg' class='target'>"
     ],
     [
      "<img src='img/2.jpg' class='image'>",
      "<img src='img/15.jpg' class='target'>"
     ],
     [
      "<img src='img/15.jpg' class='target'>",
      "<img src='img/10.jpg' class='image'>"
     ],
     [
      "<img src='img/21.jpg' class='image'>",
      "<img src='img/15.jpg' class='target'>"
     ],
     [
      "<img src='img/15.jpg' class='image'>",
      "<img src='img/3.jpg' class='target'>"
     ]
    ]
   ]
  }
 }
}