{
 "AssignmentId": "3DH6GAKTYZE6NC13EFMBYW3RO2IYZP",
 "WorkerId": "7b6d00e84f2b60223c971b6fb503181e",
 "HITId": "31ODACBENU4XREQ92B671X8VH9NSQE",
 "AssignmentStatus": "Approved",
 "AutoApprovalTime": "2020-04-01T23:25:07.000Z",
 "AcceptTime": "2020-04-01T22:50:09.000Z",
 "SubmitTime": "2020-04-01T23:20:07.000Z",
 "ApprovalTime": "2020-04-01T23:25:13.000Z",
 "answers": {
  "data": {
   "responses": "\"rt\",\"responses\",\"locator\",\"trial_type\",\"trial_index\",\"time_elapsed\",\"internal_node_id\"\r\n\"4391.565000001719\",\"{\"\"Q0\"\":\"\"bird\"\"}\",\"lookup-code-0\",\"survey-text\",\"3\",\"15652\",\"0.0-3.0-0.0-0.0\"\r\n\"4925.960000000487\",\"{\"\"Q0\"\":\"\"art\"\"}\",\"\",\"survey-text\",\"5\",\"22487\",\"0.0-5.0-0.0-0.0\"\r\n\"4689.875\",\"{\"\"Q0\"\":\"\"DA\"\"}\",\"\",\"survey-text\",\"7\",\"1217350\",\"0.0-7.0\"\r\n\"2974.279999998631\",\"{\"\"Q0\"\":\"\"bird\"\"}\",\"\",\"survey-text\",\"10\",\"1228339\",\"0.0-10.0\"\r\n\"8286.524999999674\",\"{\"\"Q0\"\":\"\"airplane\"\"}\",\"\",\"survey-text\",\"12\",\"1239238\",\"0.0-12.0\"\r\n\"2157.0300000021234\",\"{\"\"Q0\"\":\"\"gears\"\"}\",\"\",\"survey-text\",\"16\",\"1381995\",\"0.0-16.0\"\r\n\"1858.1350000021048\",\"{\"\"Q0\"\":\"\"crab\"\"}\",\"\",\"survey-text\",\"19\",\"1389974\",\"0.0-19.0\"\r\n\"3410.544999998994\",\"{\"\"Q0\"\":\"\"not apple\"\"}\",\"\",\"survey-text\",\"22\",\"1397240\",\"0.0-22.0\"\r\n\"1345.0249999987427\",\"{\"\"Q0\"\":\"\"chair\"\"}\",\"\",\"survey-text\",\"25\",\"1403445\",\"0.0-25.0\"\r\n\"2119.18499999959\",\"{\"\"Q0\"\":\"\"art\"\"}\",\"\",\"survey-text\",\"28\",\"1411172\",\"0.0-28.0\"\r\n\"2515.7999999974854\",\"{\"\"Q0\"\":\"\"art\"\"}\",\"\",\"survey-text\",\"31\",\"1418805\",\"0.0-31.0\"\r\n\"1830.814999997383\",\"{\"\"Q0\"\":\"\"art\"\"}\",\"\",\"survey-text\",\"34\",\"1426745\",\"0.0-34.0\"\r\n\"3369.060000000987\",\"{\"\"Q0\"\":\"\"car\"\"}\",\"\",\"survey-text\",\"37\",\"1434971\",\"0.0-37.0\"\r\n\"3548.5850000004284\",\"{\"\"Q0\"\":\"\"claw\"\"}\",\"\",\"survey-text\",\"40\",\"1444127\",\"0.0-40.0\"\r\n\"2623.684999998659\",\"{\"\"Q0\"\":\"\"foam\"\"}\",\"\",\"survey-text\",\"43\",\"1451862\",\"0.0-43.0\"\r\n\"3932.2450000001118\",\"{\"\"Q0\"\":\"\"slinky\"\"}\",\"\",\"survey-text\",\"46\",\"1460905\",\"0.0-46.0\"\r\n\"2198.615000001155\",\"{\"\"Q0\"\":\"\"sling\"\"}\",\"\",\"survey-text\",\"49\",\"1467712\",\"0.0-49.0\"\r\n\"7510.450000001583\",\"{\"\"Q0\"\":\"\"knob\"\"}\",\"\",\"survey-text\",\"52\",\"1481329\",\"0.0-52.0\"\r\n\"3667.7300000009127\",\"{\"\"Q0\"\":\"\"knob\"\"}\",\"\",\"survey-text\",\"55\",\"1491104\",\"0.0-55.0\"\r\n\"5052.804999999469\",\"{\"\"Q0\"\":\"\"black\"\"}\",\"\",\"survey-text\",\"58\",\"1500767\",\"0.0-58.0\"\r\n\"11140.049999998184\",\"{\"\"Q0\"\":\"\"square\"\"}\",\"\",\"survey-text\",\"61\",\"1518016\",\"0.0-61.0\"\r\n",
   "trial_info": [
    [
     "<img src = 'img/practiceTarget1.jpg' class='target'>",
     "<img src='img/practiceDistractor1.jpg' class='image'>"
    ],
    [
     "<img src='img/practiceDistractor2.jpg' class='image'>",
     "<img src ='img/practiceTarget2.jpg' class='target'>"
    ],
    [
     [
      "<img src='img/M.jpg' class='image'>",
      "<img src='img/23.jpg' class='target'>"
     ],
     [
      "<img src='img/N.jpg' class='target'>",
      "<img src='img/18.jpg' class='image'>"
     ],
     [
      "<img src='img/6.jpg' class='target'>",
      "<img src='img/A.jpg' class='image'>"
     ],
     [
      "<img src='img/2.jpg' class='image'>",
      "<img src='img/E.jpg' class='target'>"
     ],
     [
      "<img src='img/L.jpg' class='image'>",
      "<img src='img/21.jpg' class='target'>"
     ],
     [
      "<img src='img/G.jpg' class='image'>",
      "<img src='img/21.jpg' class='target'>"
     ],
     [
      "<img src='img/F.jpg' class='image'>",
      "<img src='img/21.jpg' class='target'>"
     ],
     [
      "<img src='img/21.jpg' class='image'>",
      "<img src='img/I.jpg' class='target'>"
     ],
     [
      "<img src='img/12.jpg' class='image'>",
      "<img src='img/27.jpg' class='target'>"
     ],
     [
      "<img src='img/1.jpg' class='image'>",
      "<img src='img/3.jpg' class='target'>"
     ],
     [
      "<img src='img/25.jpg' class='image'>",
      "<img src='img/17.jpg' class='target'>"
     ],
     [
      "<img src='img/16.jpg' class='image'>",
      "<img src='img/7.jpg' class='target'>"
     ],
     [
      "<img src='img/20.jpg' class='target'>",
      "<img src='img/26.jpg' class='image'>"
     ],
     [
      "<img src='img/20.jpg' class='target'>",
      "<img src='img/19.jpg' class='image'>"
     ],
     [
      "<img src='img/20.jpg' class='target'>",
      "<img src='img/9.jpg' class='image'>"
     ],
     [
      "<img src='img/20.jpg' class='image'>",
      "<img src='img/11.jpg' class='target'>"
     ]
    ]
   ]
  }
 }
}